odoo/addons/queue_job_cron/README.rst
odoo/addons/queue_job_cron/__init__.py
odoo/addons/queue_job_cron/__manifest__.py
odoo/addons/queue_job_cron/data/data.xml
odoo/addons/queue_job_cron/i18n/de.po
odoo/addons/queue_job_cron/i18n/it.po
odoo/addons/queue_job_cron/i18n/queue_job_cron.pot
odoo/addons/queue_job_cron/i18n/zh_CN.po
odoo/addons/queue_job_cron/models/__init__.py
odoo/addons/queue_job_cron/models/ir_cron.py
odoo/addons/queue_job_cron/readme/CONFIGURATION.rst
odoo/addons/queue_job_cron/readme/CONTRIBUTORS.rst
odoo/addons/queue_job_cron/readme/DESCRIPTION.rst
odoo/addons/queue_job_cron/readme/HISTORY.rst
odoo/addons/queue_job_cron/readme/INSTALL.rst
odoo/addons/queue_job_cron/readme/USAGE.rst
odoo/addons/queue_job_cron/readme/newsfragments/.gitignore
odoo/addons/queue_job_cron/static/description/icon.png
odoo/addons/queue_job_cron/static/description/index.html
odoo/addons/queue_job_cron/tests/__init__.py
odoo/addons/queue_job_cron/tests/test_queue_job_cron.py
odoo/addons/queue_job_cron/views/ir_cron_view.xml
odoo14_addon_queue_job_cron-14.0.2.0.0.dist-info/METADATA
odoo14_addon_queue_job_cron-14.0.2.0.0.dist-info/WHEEL
odoo14_addon_queue_job_cron-14.0.2.0.0.dist-info/top_level.txt
odoo14_addon_queue_job_cron-14.0.2.0.0.dist-info/RECORD
